[
  {
    "id": "a33c8631-6556-4cd6-89c9-10115f07d571",
    "event": "Starters 154",
    "resource": "https://www.codechef.com/contests",
    "date": "October 3, 2024",
    "time": "07:00 AM IST",
    "href": "https://www.codechef.comhttps://www.codechef.com/START154"
  },
  {
    "id": "51e2947b-ff53-4a86-bca1-2260924837b1",
    "event": "Starters 155",
    "resource": "https://www.codechef.com/contests",
    "date": "October 10, 2024",
    "time": "07:00 AM IST",
    "href": "https://www.codechef.comhttps://www.codechef.com/START155"
  }
]